{
  "type": "pfm:furniture",
  "group": "kitchen",
  "ingredients": [
    {
      "item": "treasure2:wither_log"
    },
    {
      "item": "treasure2:wither_log"
    },
    {
      "item": "treasure2:wither_log"
    },
    {
      "item": "treasure2:wither_log"
    },
    {
      "item": "treasure2:wither_log"
    },
    {
      "item": "treasure2:wither_log"
    },
    {
      "item": "treasure2:wither_planks"
    },
    {
      "item": "treasure2:wither_planks"
    },
    {
      "item": "treasure2:wither_planks"
    }
  ],
  "result": {
    "count": 6,
    "item": "pfm:wither_treasure2_kitchen_counter"
  }
}